bottleship/__init__.py
bottleship/bottleship.py
bottleship-0.2.4.dist-info/DESCRIPTION.rst
bottleship-0.2.4.dist-info/METADATA
bottleship-0.2.4.dist-info/RECORD
bottleship-0.2.4.dist-info/WHEEL
bottleship-0.2.4.dist-info/metadata.json
bottleship-0.2.4.dist-info/top_level.txt
