Metadata-Version: 2.0
Name: bottleship
Version: 0.2.4
Summary: Authentication for the Bottle web framework meant for very simple workflows and little-to-none user interaction
Home-page: https://github.com/omtinez/bottleship
Author: Oscar Martinez
Author-email: omtinez@gmail.com
License: MIT
Keywords: bottleship
Platform: UNKNOWN
Classifier: Development Status :: 2 - Pre-Alpha
Classifier: Intended Audience :: Developers
Classifier: License :: OSI Approved :: MIT License
Classifier: Natural Language :: English
Classifier: Programming Language :: Python :: 2
Classifier: Programming Language :: Python :: 2.6
Classifier: Programming Language :: Python :: 2.7
Classifier: Programming Language :: Python :: 3
Classifier: Programming Language :: Python :: 3.3
Classifier: Programming Language :: Python :: 3.4
Classifier: Programming Language :: Python :: 3.5
Requires-Dist: bottle
Requires-Dist: pddb
